LICENSE
entsoe_client/Clients.py
entsoe_client/ParameterTypes/Area.py
entsoe_client/ParameterTypes/AuctionCategory.py
entsoe_client/ParameterTypes/AuctionType.py
entsoe_client/ParameterTypes/BusinessType.py
entsoe_client/ParameterTypes/DocStatus.py
entsoe_client/ParameterTypes/DocumentType.py
entsoe_client/ParameterTypes/MarketAgreementType.py
entsoe_client/ParameterTypes/ProcessType.py
entsoe_client/ParameterTypes/PsrType.py
entsoe_client/ParameterTypes/__init__.py
entsoe_client/Parsers/Acknowledgment_MarketDocument_Parser.py
entsoe_client/Parsers/Balacing_MarketDocument_Parser.py
entsoe_client/Parsers/Entsoe_Document_Parser.py
entsoe_client/Parsers/GL_MarketDocument_Parser.py
entsoe_client/Parsers/Parser.py
entsoe_client/Parsers/ParserUtils.py
entsoe_client/Parsers/Publication_MarketDocument_Parser.py
entsoe_client/Parsers/TransmissionNetwork_MarketDocument_Parser.py
entsoe_client/Parsers/__init__.py
entsoe_client/Queries/Balancing/Balancing.py
entsoe_client/Queries/Balancing/__init__.py
entsoe_client/Queries/Congestion/Congestion.py
entsoe_client/Queries/Congestion/__init__.py
entsoe_client/Queries/Generation/Generation.py
entsoe_client/Queries/Generation/__init__.py
entsoe_client/Queries/Load/Load.py
entsoe_client/Queries/Load/__init__.py
entsoe_client/Queries/MasterData/MasterData.py
entsoe_client/Queries/MasterData/__init__.py
entsoe_client/Queries/Outages/Outages.py
entsoe_client/Queries/Outages/__init__.py
entsoe_client/Queries/Query.py
entsoe_client/Queries/Transmission/Transmission.py
entsoe_client/Queries/Transmission/__init__.py
entsoe_client/Queries/__init__.py
entsoe_client/Utils/ParameterEnum.py
entsoe_client/Utils/__init__.py
entsoe_client/__init__.py
entsoe_client-0.2.3.dist-info/LICENSE
entsoe_client-0.2.3.dist-info/METADATA
entsoe_client-0.2.3.dist-info/WHEEL
entsoe_client-0.2.3.dist-info/RECORD
