Metadata-Version: 2.1
Name: entsoe-client
Version: 0.2.3
Summary: Formulate human-readable queries and retrieve data from ENTSO-E into pandas.DataFrame format.
Home-page: https://github.com/DarioHett/entsoe-client
License: MIT
Keywords: entsoe,entso-e,power,electricity,europe,tso,transparency platform
Author: Dario Hett
Author-email: dariohett@gmail.com
Requires-Python: >=3.9,<4.0
Classifier: Development Status :: 3 - Alpha
Classifier: Intended Audience :: Developers
Classifier: Intended Audience :: Science/Research
Classifier: License :: OSI Approved :: MIT License
Classifier: Operating System :: OS Independent
Classifier: Programming Language :: Python :: 3
Classifier: Programming Language :: Python :: 3.9
Classifier: Programming Language :: Python :: 3.10
Classifier: Programming Language :: Python :: 3.11
Classifier: Programming Language :: Python :: 3.12
Classifier: Topic :: Scientific/Engineering
Requires-Dist: arrow (>=1.1.1,<2.0.0)
Requires-Dist: beautifulsoup4 (>=4.9.3,<5.0.0)
Requires-Dist: lxml (>=4.6.3,<5.0.0)
Requires-Dist: pandas (>=2.1.4)
Requires-Dist: python-dateutil (>=2.8.2,<3.0.0)
Requires-Dist: pytz (>=2021.1,<2022.0)
Requires-Dist: requests (>=2.26.0,<3.0.0)
Requires-Dist: tenacity (>=8.0.1,<9.0.0)
Project-URL: Repository, https://github.com/DarioHett/entsoe-client
